helloworld.py
helloworld_y24ved-0.0.1.dist-info/LICENSE
helloworld_y24ved-0.0.1.dist-info/METADATA
helloworld_y24ved-0.0.1.dist-info/WHEEL
helloworld_y24ved-0.0.1.dist-info/top_level.txt
helloworld_y24ved-0.0.1.dist-info/RECORD
