Metadata-Version: 2.1
Name: helloworld-y24ved
Version: 0.0.1
Summary: Say hello
Home-page: https://github.com/y24ved/helloworld
Author: y24 ved
Author-email: y24.ved@gmail.com
License: UNKNOWN
Platform: UNKNOWN
Classifier: Programming Language :: Python :: 3
Classifier: Programming Language :: Python :: 3.10
Classifier: License :: OSI Approved :: GNU General Public License v2 (GPLv2)
Classifier: Operating System :: OS Independent
License-File: LICENSE
Requires-Dist: click (~=8.0.4)
Provides-Extra: dev
Requires-Dist: pytest (>=7.0.1) ; extra == 'dev'
